odoo_analyse/__init__.py
odoo_analyse/__main__.py
odoo_analyse/field.py
odoo_analyse/function.py
odoo_analyse/js_module.py
odoo_analyse/model.py
odoo_analyse/module.py
odoo_analyse/odoo.py
odoo_analyse/record.py
odoo_analyse/utils.py
odoo_analyse-2.0.0.dist-info/LICENSE
odoo_analyse-2.0.0.dist-info/METADATA
odoo_analyse-2.0.0.dist-info/WHEEL
odoo_analyse-2.0.0.dist-info/entry_points.txt
odoo_analyse-2.0.0.dist-info/top_level.txt
odoo_analyse-2.0.0.dist-info/RECORD
