Metadata-Version: 2.1
Name: odoo-analyse
Version: 2.0.0
Summary: Package to analyse odoo modules
Home-page: https://github.com/initOS/odoo-analyse
Author: initOS GmbH
Author-email: info@initos.com
License: LGPL-3.0
Project-URL: Documentation, https://github.com/initOS/odoo-analyse/blob/master/README.md
Project-URL: Usage, https://odoo-code-search.com
Keywords: odoo modules analyze dependency graph
Classifier: Development Status :: 5 - Production/Stable
Classifier: License :: OSI Approved :: GNU Lesser General Public License v3 (LGPLv3)
Classifier: Topic :: Software Development
Requires-Python: >=3.6
License-File: LICENSE
Requires-Dist: 2to3
Requires-Dist: cloc
Requires-Dist: lxml
Requires-Dist: mccabe
Requires-Dist: radon
Provides-Extra: graph
Requires-Dist: graphviz ; extra == 'graph'
Requires-Dist: psycopg2 ; extra == 'graph'
